{
  "objectInfo" : {
    "id" : "1SpMttVJROGbUBw83f8QKZ",
    "name" : "mct_m_seqGen_multi_source",
    "type" : "MTT",
    "metadata" : {
      "modelVersion" : {
        "major" : 0,
        "minor" : 0
      },
      "repoInfo" : {
        "repoHandle" : "0100060Z000000000012"
      },
      "contextAttributes" : [ {
        "name" : "id",
        "value" : "@1"
      } ],
      "additionalInfo" : {
        "description" : "Using Multi-source using Custom relationship",
        "contentType" : "JSON",
        "documentState" : "VALID"
      }
    }
  },
  "dataFileExtension" : "zip",
  "objectRefs" : [ {
    "id" : "bUKcS4wpRKeeD5et9ENNsA",
    "name" : "SK_Con_MySQL_Auto",
    "type" : "Connection",
    "metadata" : {
      "modelVersion" : {
        "major" : 0,
        "minor" : 0
      },
      "repoInfo" : {
        "repoHandle" : "0100060B000000000004"
      },
      "contextAttributes" : null,
      "additionalInfo" : {
        "description" : "MySQL connection for CMD Sorter automation",
        "contentType" : "JSON",
        "documentState" : "COMPLETE"
      }
    },
    "path" : "/SYS"
  }, {
    "id" : "0J4MmvORA6kfyGhrkNg3gd",
    "name" : "m_seqGen_multi_source",
    "type" : "DTEMPLATE",
    "metadata" : {
      "modelVersion" : {
        "major" : 0,
        "minor" : 0
      },
      "repoInfo" : {
        "repoHandle" : "0100061700000000001J"
      },
      "contextAttributes" : [ {
        "name" : "id",
        "value" : "@1"
      } ],
      "additionalInfo" : {
        "description" : "SeqGen to get input from Multi-obj source - Custom relationship",
        "contentType" : "JSON",
        "documentState" : "VALID"
      }
    },
    "path" : "/Explore/GA/SeqGen"
  }, {
    "id" : "3bed8p78hNwgdgZdjZvK8C",
    "name" : "SK_Con_FF_Auto",
    "type" : "Connection",
    "metadata" : {
      "modelVersion" : {
        "major" : 0,
        "minor" : 0
      },
      "repoInfo" : {
        "repoHandle" : "0100060B000000000003"
      },
      "contextAttributes" : null,
      "additionalInfo" : {
        "description" : "Flat File connection for CMD Sorter Automation",
        "contentType" : "JSON",
        "documentState" : "COMPLETE"
      }
    },
    "path" : "/SYS"
  }, {
    "id" : "5CBl81s4ZoUju8s2LD3EEO",
    "name" : "psvrlxfrs2004",
    "type" : "AgentGroup",
    "metadata" : {
      "modelVersion" : {
        "major" : 0,
        "minor" : 0
      },
      "repoInfo" : {
        "repoHandle" : "01000625000000000004"
      },
      "contextAttributes" : null,
      "additionalInfo" : {
        "description" : null,
        "contentType" : "JSON",
        "documentState" : "VALID"
      }
    },
    "path" : "/SYS"
  } ]
}